bits/__init__.py
bits/github/__init__.py
bits/github/app.py
bits/github/auditlogs.py
bits/github/client.py
bits/github/datastore.py
bits/github/firestore.py
bits/github/helpers.py
bits/github/sync.py
bits/github/update.py
bits_github-1.6.1.dist-info/METADATA
bits_github-1.6.1.dist-info/WHEEL
bits_github-1.6.1.dist-info/RECORD
