Metadata-Version: 2.4
Name: bits-github
Version: 1.6.1
Summary: BITS GitHub Package for Python
License-Expression: BSD-3-Clause
Keywords: bits,github
Author: Dev Null
Author-email: <devnull@broadinstitute.org>
Requires-Python: >=3.9
Classifier: Programming Language :: Python :: 3
Classifier: Programming Language :: Python :: 3.9
Classifier: Programming Language :: Python :: 3.10
Classifier: Programming Language :: Python :: 3.11
Classifier: Programming Language :: Python :: 3.12
Classifier: Programming Language :: Python :: 3.13
Classifier: Programming Language :: Python :: 3.14
Requires-Dist: bits-google (>=2.0.0,<3.0.0)
Requires-Dist: google-cloud-datastore (>=2.19.0,<3.0.0)
Requires-Dist: google-cloud-firestore (>=2.15.0,<3.0.0)
Requires-Dist: python-dateutil (>=2.9.0.post0,<3.0.0)
Requires-Dist: pytz
Project-URL: Homepage, https://github.com/broadinstitute/bits-github.git
Project-URL: Repository, https://github.com/broadinstitute/bits-github.git
